<?xml version="1.0" encoding="UTF-8"?>
<!DOCTYPE mapper PUBLIC "-//mybatis.org//DTD Mapper 3.0//EN" "http://mybatis.org/dtd/mybatis-3-mapper.dtd">
<mapper namespace="com.xue.cookbook.auth.dao.AuthPermissionsMapper">
  <resultMap id="BaseResultMap" type="com.xue.cookbook.auth.model.AuthPermissions">
    <!--
      WARNING - @mbg.generated
      This element is automatically generated by MyBatis Generator, do not modify.
    -->
    <id column="id" jdbcType="INTEGER" property="id" />
    <result column="name" jdbcType="VARCHAR" property="name" />
    <result column="custom_name" jdbcType="VARCHAR" property="customName" />
    <result column="url" jdbcType="VARCHAR" property="url" />
    <result column="code" jdbcType="VARCHAR" property="code" />
    <result column="parent_id" jdbcType="INTEGER" property="parentId" />
    <result column="path" jdbcType="VARCHAR" property="path" />
    <result column="level" jdbcType="TINYINT" property="level" />
    <result column="is_leaf" jdbcType="TINYINT" property="isLeaf" />
    <result column="method" jdbcType="VARCHAR" property="method" />
    <result column="sort" jdbcType="INTEGER" property="sort" />
    <result column="created_at" jdbcType="TIMESTAMP" property="createdAt" />
    <result column="updated_at" jdbcType="TIMESTAMP" property="updatedAt" />
  </resultMap>
  <delete id="deleteByPrimaryKey" parameterType="java.lang.Integer">
    <!--
      WARNING - @mbg.generated
      This element is automatically generated by MyBatis Generator, do not modify.
    -->
    delete from auth_permissions
    where id = #{id,jdbcType=INTEGER}
  </delete>
  <insert id="insert" parameterType="com.xue.cookbook.auth.model.AuthPermissions">
    <!--
      WARNING - @mbg.generated
      This element is automatically generated by MyBatis Generator, do not modify.
    -->
    insert into auth_permissions (id, `name`, custom_name, 
      url, code, parent_id, 
      `path`, `level`, is_leaf, 
      `method`, sort, created_at, 
      updated_at)
    values (#{id,jdbcType=INTEGER}, #{name,jdbcType=VARCHAR}, #{customName,jdbcType=VARCHAR}, 
      #{url,jdbcType=VARCHAR}, #{code,jdbcType=VARCHAR}, #{parentId,jdbcType=INTEGER}, 
      #{path,jdbcType=VARCHAR}, #{level,jdbcType=TINYINT}, #{isLeaf,jdbcType=TINYINT}, 
      #{method,jdbcType=VARCHAR}, #{sort,jdbcType=INTEGER}, #{createdAt,jdbcType=TIMESTAMP}, 
      #{updatedAt,jdbcType=TIMESTAMP})
  </insert>
  <update id="updateByPrimaryKey" parameterType="com.xue.cookbook.auth.model.AuthPermissions">
    <!--
      WARNING - @mbg.generated
      This element is automatically generated by MyBatis Generator, do not modify.
    -->
    update auth_permissions
    set `name` = #{name,jdbcType=VARCHAR},
      custom_name = #{customName,jdbcType=VARCHAR},
      url = #{url,jdbcType=VARCHAR},
      code = #{code,jdbcType=VARCHAR},
      parent_id = #{parentId,jdbcType=INTEGER},
      `path` = #{path,jdbcType=VARCHAR},
      `level` = #{level,jdbcType=TINYINT},
      is_leaf = #{isLeaf,jdbcType=TINYINT},
      `method` = #{method,jdbcType=VARCHAR},
      sort = #{sort,jdbcType=INTEGER},
      created_at = #{createdAt,jdbcType=TIMESTAMP},
      updated_at = #{updatedAt,jdbcType=TIMESTAMP}
    where id = #{id,jdbcType=INTEGER}
  </update>
  <select id="selectByPrimaryKey" parameterType="java.lang.Integer" resultMap="BaseResultMap">
    <!--
      WARNING - @mbg.generated
      This element is automatically generated by MyBatis Generator, do not modify.
    -->
    select id, `name`, custom_name, url, code, parent_id, `path`, `level`, is_leaf, `method`, 
    sort, created_at, updated_at
    from auth_permissions
    where id = #{id,jdbcType=INTEGER}
  </select>
  <select id="selectAll" resultMap="BaseResultMap">
    <!--
      WARNING - @mbg.generated
      This element is automatically generated by MyBatis Generator, do not modify.
    -->
    select id, `name`, custom_name, url, code, parent_id, `path`, `level`, is_leaf, `method`, 
    sort, created_at, updated_at
    from auth_permissions
  </select>
</mapper>